py_olamaps/OlaMaps.py
py_olamaps/__init__.py
py_olamaps/exceptions.py
py_olamaps/resources/__init__.py
py_olamaps/resources/geocode.py
py_olamaps/resources/map_tiles.py
py_olamaps/resources/places.py
py_olamaps/resources/roads.py
py_olamaps/resources/routing.py
py_olamaps/utils/CommonEnums.py
py_olamaps/utils/__init__.py
py_olamaps-0.4.0.dist-info/METADATA
py_olamaps-0.4.0.dist-info/WHEEL
py_olamaps-0.4.0.dist-info/RECORD
