Metadata-Version: 2.1
Name: py-olamaps
Version: 0.4.0
Summary: Python client library for Ola Maps API Services
Author: Lav Sharma
Author-email: lavsharma2016@gmail.com
Requires-Python: >=3.9,<4.0
Classifier: Programming Language :: Python :: 3
Classifier: Programming Language :: Python :: 3.9
Classifier: Programming Language :: Python :: 3.10
Classifier: Programming Language :: Python :: 3.11
Classifier: Programming Language :: Python :: 3.12
Requires-Dist: retrying (>=1.3.4,<2.0.0)
